ChangeLog
LICENSE
MANIFEST.in
README.rst
setup.py
redirbot/__init__.py
redirbot.egg-info/PKG-INFO
redirbot.egg-info/SOURCES.txt
redirbot.egg-info/dependency_links.txt
redirbot.egg-info/entry_points.txt
redirbot.egg-info/requires.txt
redirbot.egg-info/top_level.txt
redirbot/data/config/config.ini