Metadata-Version: 1.1
Name: redirbot
Version: 0.0.5
Summary: IRCBot, telling people they should contact you on different nickname
Home-page: https://github.com/yaccz/redirbot
Author: Jan Matejka
Author-email: yac@blesmrt.net
License: UNKNOWN
Platform: UNKNOWN
Classifier: Operating System :: POSIX
Classifier: License :: OSI Approved :: BSD License
Classifier: Programming Language :: Python
Classifier: Development Status :: 4 - Beta
Classifier: Framework :: Twisted
Classifier: Intended Audience :: End Users/Desktop
Classifier: Intended Audience :: System Administrators
Classifier: Environment :: No Input/Output (Daemon)
Classifier: Natural Language :: English
Classifier: Topic :: Communications :: Chat :: Internet Relay Chat
